ksylint/__init__.py
ksylint/ksy_schema.json
ksylint/lint.py
ksylint/order.py
ksylint/yamllint_config.py
ksylint-0.3.1.dist-info/LICENSE
ksylint-0.3.1.dist-info/METADATA
ksylint-0.3.1.dist-info/WHEEL
ksylint-0.3.1.dist-info/entry_points.txt
ksylint-0.3.1.dist-info/top_level.txt
ksylint-0.3.1.dist-info/RECORD
