Metadata-Version: 2.1
Name: ksylint
Version: 0.3.1
Summary: A linter for ksy files.
Home-page: http://github.com/cugu/ksylint
Author: Jonas Plum
License: GPL-3.0-or-later
Platform: UNKNOWN
Requires-Python: >=3.6
Requires-Dist: yamllint (==1.17.0)
Requires-Dist: jsonschema (==3.0.2)
Requires-Dist: PyYAML (==5.1.2)
